gamemergency/NumberMatch.py
gamemergency/RSP.py
gamemergency/RSPsqure.py
gamemergency/__init__.py
gamemergency/scoreboard.py
gamemergency/tictactoe.py
gamemergency-0.0.2.dist-info/METADATA
gamemergency-0.0.2.dist-info/WHEEL
gamemergency-0.0.2.dist-info/top_level.txt
gamemergency-0.0.2.dist-info/RECORD
