Metadata-Version: 2.1
Name: gamemergency
Version: 0.0.2
Summary: minigame library
Home-page: https://github.com/Leafguyk/gamemergency
Download-URL: https://github.com/Leafguyk/gamemergency/archive/master.zip
Author: Leafguyk, qwerdf12345677, jennyiris06, aslkf
Author-email: leafguykk@gmail.com
Keywords: minigame
Classifier: Programming Language :: Python :: 3
Classifier: Programming Language :: Python :: 3.2
Classifier: Programming Language :: Python :: 3.3
Classifier: Programming Language :: Python :: 3.4
Classifier: Programming Language :: Python :: 3.5
Classifier: Programming Language :: Python :: 3.6
Classifier: Programming Language :: Python :: 3.7
Requires-Python: >=3
